autopysta/_autopysta.so
autopysta/__init__.py
autopysta/VERSION
autopysta/_autopysta.pyi
autopysta/modeling.py
autopysta/trajectory_reader.py
autopysta-0.0.40.1.dist-info/RECORD
autopysta-0.0.40.1.dist-info/WHEEL
autopysta-0.0.40.1.dist-info/top_level.txt
autopysta-0.0.40.1.dist-info/METADATA
