Metadata-Version: 2.1
Name: autopysta
Version: 0.0.40.1
Summary: 2D traffic modeling.
Home-page: https://bitbucket.org/rdelpiano/autopysta/
Author: Rafael Delpiano
License: MIT
Classifier: Programming Language :: Python :: 3
Classifier: Operating System :: OS Independent
Requires-Python: >=3.8
Requires-Dist: matplotlib
Requires-Dist: numpy
